{
	"ext": [
		"nowiki",
		"pre",
		"gallery",
		"indicator",
		"poem",
		"ref",
		"references",
		"charinsert",
		"choose",
		"score",
		"seo",
		"tab",
		"tabs",
		"combobox",
		"combooption"
	],
	"html": [
		[
			"b",
			"bdi",
			"del",
			"i",
			"ins",
			"u",
			"font",
			"big",
			"small",
			"sub",
			"sup",
			"h1",
			"h2",
			"h3",
			"h4",
			"h5",
			"h6",
			"cite",
			"code",
			"em",
			"s",
			"strike",
			"strong",
			"tt",
			"var",
			"div",
			"center",
			"blockquote",
			"ol",
			"ul",
			"dl",
			"table",
			"caption",
			"pre",
			"ruby",
			"rb",
			"rp",
			"rt",
			"rtc",
			"p",
			"span",
			"abbr",
			"dfn",
			"kbd",
			"samp",
			"data",
			"time",
			"mark",
			"tr",
			"td",
			"th",
			"q",
			"bdo"
		],
		[
			"li",
			"dt",
			"dd"
		],
		[
			"br",
			"wbr",
			"hr",
			"meta",
			"link"
		]
	],
	"namespaces": {
		"-2": "Media",
		"-1": "Special",
		"0": "",
		"1": "Talk",
		"2": "User",
		"3": "User talk",
		"4": "Project",
		"5": "Project talk",
		"6": "File",
		"7": "File talk",
		"8": "MediaWiki",
		"9": "MediaWiki talk",
		"10": "Template",
		"11": "Template talk",
		"12": "Help",
		"13": "Help talk",
		"14": "Category",
		"15": "Category talk",
		"274": "Widget",
		"275": "Widget talk",
		"828": "Module",
		"829": "Module talk"
	},
	"nsid": {
		"": 0,
		"media": -2,
		"媒体": -2,
		"媒体文件": -2,
		"媒體": -2,
		"special": -1,
		"特殊": -1,
		"talk": 1,
		"对话": 1,
		"對話": 1,
		"讨论": 1,
		"討論": 1,
		"user": 2,
		"使用者": 2,
		"用戶": 2,
		"用户": 2,
		"user talk": 3,
		"使用者討論": 3,
		"用戶對話": 3,
		"用戶討論": 3,
		"用户对话": 3,
		"用户讨论": 3,
		"llwiki": 4,
		"project": 4,
		"llwiki talk": 5,
		"llwiki讨论": 5,
		"llwiki討論": 5,
		"project talk": 5,
		"file": 6,
		"image": 6,
		"图像": 6,
		"圖像": 6,
		"文件": 6,
		"档案": 6,
		"檔案": 6,
		"file talk": 7,
		"image talk": 7,
		"图像对话": 7,
		"图像讨论": 7,
		"圖像對話": 7,
		"圖像討論": 7,
		"文件对话": 7,
		"文件讨论": 7,
		"文件對話": 7,
		"文件討論": 7,
		"档案对话": 7,
		"档案讨论": 7,
		"檔案對話": 7,
		"檔案討論": 7,
		"mediawiki": 8,
		"mediawiki talk": 9,
		"mediawiki讨论": 9,
		"mediawiki討論": 9,
		"template": 10,
		"样板": 10,
		"模板": 10,
		"樣板": 10,
		"template talk": 11,
		"样板对话": 11,
		"样板讨论": 11,
		"模板对话": 11,
		"模板讨论": 11,
		"模板對話": 11,
		"模板討論": 11,
		"樣板對話": 11,
		"樣板討論": 11,
		"help": 12,
		"使用說明": 12,
		"帮助": 12,
		"幫助": 12,
		"help talk": 13,
		"使用說明討論": 13,
		"帮助对话": 13,
		"帮助讨论": 13,
		"幫助對話": 13,
		"幫助討論": 13,
		"category": 14,
		"分类": 14,
		"分類": 14,
		"category talk": 15,
		"分类对话": 15,
		"分类讨论": 15,
		"分類對話": 15,
		"分類討論": 15,
		"widget": 274,
		"小元件": 274,
		"小组件": 274,
		"小部件": 274,
		"微件": 274,
		"widget talk": 275,
		"小元件讨论": 275,
		"小组件讨论": 275,
		"小部件讨论": 275,
		"微件讨论": 275,
		"微件討論": 275,
		"module": 828,
		"模块": 828,
		"模組": 828,
		"module talk": 829,
		"模块讨论": 829,
		"模組討論": 829
	},
	"variable": [
		"!",
		"=",
		"currentmonth",
		"currentmonth1",
		"currentmonthname",
		"currentmonthnamegen",
		"currentmonthabbrev",
		"currentday",
		"currentday2",
		"currentdayname",
		"currentyear",
		"currenttime",
		"currenthour",
		"localmonth",
		"localmonth1",
		"localmonthname",
		"localmonthnamegen",
		"localmonthabbrev",
		"localday",
		"localday2",
		"localdayname",
		"localyear",
		"localtime",
		"localhour",
		"numberofarticles",
		"numberoffiles",
		"numberofedits",
		"articlepath",
		"pageid",
		"sitename",
		"server",
		"servername",
		"scriptpath",
		"stylepath",
		"pagename",
		"pagenamee",
		"fullpagename",
		"fullpagenamee",
		"namespace",
		"namespacee",
		"namespacenumber",
		"currentweek",
		"currentdow",
		"localweek",
		"localdow",
		"revisionid",
		"revisionday",
		"revisionday2",
		"revisionmonth",
		"revisionmonth1",
		"revisionyear",
		"revisiontimestamp",
		"revisionuser",
		"revisionsize",
		"subpagename",
		"subpagenamee",
		"talkspace",
		"talkspacee",
		"subjectspace",
		"subjectspacee",
		"talkpagename",
		"talkpagenamee",
		"subjectpagename",
		"subjectpagenamee",
		"numberofusers",
		"numberofactiveusers",
		"numberofpages",
		"currentversion",
		"rootpagename",
		"rootpagenamee",
		"basepagename",
		"basepagenamee",
		"currenttimestamp",
		"localtimestamp",
		"directionmark",
		"contentlanguage",
		"pagelanguage",
		"numberofadmins",
		"cascadingsources"
	],
	"parserFunction": [
		{
			"ns": "ns",
			"名称空间": "ns",
			"nse": "nse",
			"名称空间e": "nse",
			"urlencode": "urlencode",
			"url编码": "urlencode",
			"lcfirst": "lcfirst",
			"小写首字": "lcfirst",
			"ucfirst": "ucfirst",
			"大写首字": "ucfirst",
			"lc": "lc",
			"小写": "lc",
			"uc": "uc",
			"大写": "uc",
			"localurl": "localurl",
			"本地url": "localurl",
			"localurle": "localurle",
			"本地urle": "localurle",
			"fullurl": "fullurl",
			"完整url": "fullurl",
			"fullurle": "fullurle",
			"完整url等同": "fullurle",
			"canonicalurl": "canonicalurl",
			"规范url": "canonicalurl",
			"canonicalurle": "canonicalurle",
			"规范url等同": "canonicalurle",
			"formatnum": "formatnum",
			"格式化数字": "formatnum",
			"grammar": "grammar",
			"语法": "grammar",
			"gender": "gender",
			"性别": "gender",
			"plural": "plural",
			"复数": "plural",
			"bidi": "bidi",
			"#language": "language",
			"#语言": "language",
			"padleft": "padleft",
			"左填充": "padleft",
			"padright": "padright",
			"右填充": "padright",
			"anchorencode": "anchorencode",
			"锚编码": "anchorencode",
			"filepath": "filepath",
			"文件路径": "filepath",
			"pageid": "pageid",
			"页面id": "pageid",
			"int": "int",
			"界面": "int",
			"#special": "special",
			"#特殊": "special",
			"#speciale": "speciale",
			"#特殊等同": "speciale",
			"#tag": "tag",
			"#标记": "tag",
			"#formatdate": "formatdate",
			"#dateformat": "formatdate",
			"#日期格式化": "formatdate",
			"#格式化日期": "formatdate",
			"#invoke": "invoke",
			"#调用": "invoke",
			"#while": "while",
			"#dowhile": "dowhile",
			"#loop": "loop",
			"#forargs": "forargs",
			"#fornumargs": "fornumargs",
			"#if": "if",
			"#如果": "if",
			"#若": "if",
			"#非空式": "if",
			"#ifeq": "ifeq",
			"#匹配式": "ifeq",
			"#如果相等": "ifeq",
			"#相同式": "ifeq",
			"#若相等": "ifeq",
			"#switch": "switch",
			"#双射式": "switch",
			"#多条件式": "switch",
			"#多选式": "switch",
			"#开关": "switch",
			"#转换": "switch",
			"#ifexist": "ifexist",
			"#如有": "ifexist",
			"#存在式": "ifexist",
			"#若有": "ifexist",
			"#ifexpr": "ifexpr",
			"#若表达式": "ifexpr",
			"#iferror": "iferror",
			"#如果错误": "iferror",
			"#错误式": "iferror",
			"#time": "time",
			"#时间": "time",
			"#timel": "timel",
			"#时间l": "timel",
			"#expr": "expr",
			"#表达式": "expr",
			"#计算式": "expr",
			"#rel2abs": "rel2abs",
			"#titleparts": "titleparts",
			"#标题组成部分": "titleparts",
			"#urldecode": "urldecode",
			"#url解码": "urldecode",
			"#choose": "choose",
			"#var": "var",
			"#varexists": "varexists",
			"#var_final": "var_final",
			"#vardefine": "vardefine",
			"#vardefineecho": "vardefineecho",
			"#widget": "widget",
			"#小元件": "widget",
			"#小组件": "widget",
			"#小部件": "widget",
			"#微件": "widget",
			"articlepath": "articlepath",
			"条目路径": "articlepath",
			"server": "server",
			"服务器": "server",
			"servername": "servername",
			"服务器名": "servername",
			"scriptpath": "scriptpath",
			"脚本路径": "scriptpath",
			"stylepath": "stylepath",
			"样式路径": "stylepath",
			"msgnw": "msgnw",
			"#regex": "regex",
			"#regex_var": "regex_var",
			"#regexquote": "regexquote",
			"#regexall": "regexall",
			"#len": "len",
			"#长度": "len",
			"#pos": "pos",
			"#位置": "pos",
			"#终端": "pos",
			"#rpos": "rpos",
			"#反终端": "rpos",
			"#最近位置": "rpos",
			"#sub": "sub",
			"#pf子": "sub",
			"#截取": "sub",
			"#count": "count",
			"#计数": "count",
			"#rmatch": "rmatch",
			"#重新匹配": "rmatch",
			"#rreplace": "rreplace",
			"#重新取代": "rreplace",
			"#replace": "replace",
			"#取代": "replace",
			"#替换": "replace",
			"#rsplit": "rsplit",
			"#重新分解": "rsplit",
			"#explode": "explode",
			"#炸开": "explode",
			"#爆炸": "explode",
			"#粉碎": "explode",
			"#tab": "tab",
			"#seo": "seo"
		},
		{
			"页面数": "numberofpages",
			"NUMBEROFPAGES": "numberofpages",
			"用户数": "numberofusers",
			"NUMBEROFUSERS": "numberofusers",
			"活跃用户数": "numberofactiveusers",
			"NUMBEROFACTIVEUSERS": "numberofactiveusers",
			"条目数": "numberofarticles",
			"NUMBEROFARTICLES": "numberofarticles",
			"文件数": "numberoffiles",
			"NUMBEROFFILES": "numberoffiles",
			"管理员数": "numberofadmins",
			"NUMBEROFADMINS": "numberofadmins",
			"组中用户数": "numberingroup",
			"NUMBERINGROUP": "numberingroup",
			"NUMINGROUP": "numberingroup",
			"编辑数": "numberofedits",
			"NUMBEROFEDITS": "numberofedits",
			"默认排序": "defaultsort",
			"默认排序关键字": "defaultsort",
			"默认分类排序": "defaultsort",
			"DEFAULTSORT": "defaultsort",
			"DEFAULTSORTKEY": "defaultsort",
			"DEFAULTCATEGORYSORT": "defaultsort",
			"分类中页面数": "pagesincategory",
			"PAGESINCATEGORY": "pagesincategory",
			"PAGESINCAT": "pagesincategory",
			"页面大小": "pagesize",
			"PAGESIZE": "pagesize",
			"保护级别": "protectionlevel",
			"PROTECTIONLEVEL": "protectionlevel",
			"PROTECTIONEXPIRY": "protectionexpiry",
			"名字空间等同": "namespacee",
			"NAMESPACEE": "namespacee",
			"名字空间编号": "namespacenumber",
			"NAMESPACENUMBER": "namespacenumber",
			"讨论空间": "talkspace",
			"讨论名字空间": "talkspace",
			"TALKSPACE": "talkspace",
			"讨论空间等同": "talkspacee",
			"讨论名字空间等同": "talkspacee",
			"TALKSPACEE": "talkspacee",
			"主名字空间": "subjectspace",
			"条目名字空间": "subjectspace",
			"SUBJECTSPACE": "subjectspace",
			"ARTICLESPACE": "subjectspace",
			"主名字空间等同": "subjectspacee",
			"条目名字空间等同": "subjectspacee",
			"SUBJECTSPACEE": "subjectspacee",
			"ARTICLESPACEE": "subjectspacee",
			"页名": "pagename",
			"页面名": "pagename",
			"页面名称": "pagename",
			"PAGENAME": "pagename",
			"页面名等同": "pagenamee",
			"页面名称等同": "pagenamee",
			"PAGENAMEE": "pagenamee",
			"页面全称": "fullpagename",
			"完整页面名称": "fullpagename",
			"FULLPAGENAME": "fullpagename",
			"完整页面名称等同": "fullpagenamee",
			"FULLPAGENAMEE": "fullpagenamee",
			"根页面名称": "rootpagename",
			"ROOTPAGENAME": "rootpagename",
			"根页面名称等同": "rootpagenamee",
			"ROOTPAGENAMEE": "rootpagenamee",
			"基础页面名称": "basepagename",
			"BASEPAGENAME": "basepagename",
			"基础页面名称等同": "basepagenamee",
			"BASEPAGENAMEE": "basepagenamee",
			"子页面名称": "subpagename",
			"SUBPAGENAME": "subpagename",
			"子页面名称等同": "subpagenamee",
			"SUBPAGENAMEE": "subpagenamee",
			"讨论页面名称": "talkpagename",
			"对话页面名称": "talkpagename",
			"TALKPAGENAME": "talkpagename",
			"讨论页面名称等同": "talkpagenamee",
			"对话页面名称等同": "talkpagenamee",
			"TALKPAGENAMEE": "talkpagenamee",
			"主名字空间页面名称": "subjectpagename",
			"条目页面名称": "subjectpagename",
			"SUBJECTPAGENAME": "subjectpagename",
			"ARTICLEPAGENAME": "subjectpagename",
			"主名字空间页面名称等同": "subjectpagenamee",
			"条目页面名称等同": "subjectpagenamee",
			"SUBJECTPAGENAMEE": "subjectpagenamee",
			"ARTICLEPAGENAMEE": "subjectpagenamee",
			"修订ID": "revisionid",
			"REVISIONID": "revisionid",
			"修订日": "revisionday",
			"REVISIONDAY": "revisionday",
			"修订日2": "revisionday2",
			"REVISIONDAY2": "revisionday2",
			"修订月": "revisionmonth",
			"REVISIONMONTH": "revisionmonth",
			"修订月1": "revisionmonth1",
			"REVISIONMONTH1": "revisionmonth1",
			"修订年": "revisionyear",
			"REVISIONYEAR": "revisionyear",
			"修订时间戳": "revisiontimestamp",
			"REVISIONTIMESTAMP": "revisiontimestamp",
			"修订用户": "revisionuser",
			"REVISIONUSER": "revisionuser",
			"级联来源": "cascadingsources",
			"CASCADINGSOURCES": "cascadingsources",
			"名字空间": "namespace",
			"NAMESPACE": "namespace",
			"显示标题": "displaytitle",
			"DISPLAYTITLE": "displaytitle",
			"!": "!",
			"本月": "currentmonth",
			"本月2": "currentmonth",
			"CURRENTMONTH": "currentmonth",
			"CURRENTMONTH2": "currentmonth",
			"本月1": "currentmonth1",
			"CURRENTMONTH1": "currentmonth1",
			"本月名": "currentmonthname",
			"本月名称": "currentmonthname",
			"CURRENTMONTHNAME": "currentmonthname",
			"本月名属格": "currentmonthnamegen",
			"本月名称属格": "currentmonthnamegen",
			"CURRENTMONTHNAMEGEN": "currentmonthnamegen",
			"本月简称": "currentmonthabbrev",
			"CURRENTMONTHABBREV": "currentmonthabbrev",
			"今天": "currentday",
			"CURRENTDAY": "currentday",
			"今天2": "currentday2",
			"CURRENTDAY2": "currentday2",
			"星期": "currentdayname",
			"今天名": "currentdayname",
			"今天名称": "currentdayname",
			"CURRENTDAYNAME": "currentdayname",
			"今年": "currentyear",
			"CURRENTYEAR": "currentyear",
			"当前时间": "currenttime",
			"此时": "currenttime",
			"CURRENTTIME": "currenttime",
			"当前小时": "currenthour",
			"CURRENTHOUR": "currenthour",
			"本地月": "localmonth",
			"本地月2": "localmonth",
			"LOCALMONTH": "localmonth",
			"LOCALMONTH2": "localmonth",
			"本地月1": "localmonth1",
			"LOCALMONTH1": "localmonth1",
			"本地月份名": "localmonthname",
			"LOCALMONTHNAME": "localmonthname",
			"本地月历": "localmonthnamegen",
			"LOCALMONTHNAMEGEN": "localmonthnamegen",
			"本地月缩写": "localmonthabbrev",
			"LOCALMONTHABBREV": "localmonthabbrev",
			"本地日": "localday",
			"LOCALDAY": "localday",
			"本地日2": "localday2",
			"LOCALDAY2": "localday2",
			"本地日名": "localdayname",
			"LOCALDAYNAME": "localdayname",
			"本地年": "localyear",
			"LOCALYEAR": "localyear",
			"本地时间": "localtime",
			"LOCALTIME": "localtime",
			"本地小时": "localhour",
			"LOCALHOUR": "localhour",
			"站点名称": "sitename",
			"SITENAME": "sitename",
			"本周": "currentweek",
			"CURRENTWEEK": "currentweek",
			"当前DOW": "currentdow",
			"CURRENTDOW": "currentdow",
			"本地周": "localweek",
			"LOCALWEEK": "localweek",
			"本地DOW": "localdow",
			"LOCALDOW": "localdow",
			"修订大小": "revisionsize",
			"REVISIONSIZE": "revisionsize",
			"当前版本": "currentversion",
			"CURRENTVERSION": "currentversion",
			"当前时间戳": "currenttimestamp",
			"CURRENTTIMESTAMP": "currenttimestamp",
			"本地时间戳": "localtimestamp",
			"LOCALTIMESTAMP": "localtimestamp",
			"方向标记": "directionmark",
			"DIRECTIONMARK": "directionmark",
			"DIRMARK": "directionmark",
			"内容语言": "contentlanguage",
			"CONTENTLANGUAGE": "contentlanguage",
			"CONTENTLANG": "contentlanguage",
			"PAGELANGUAGE": "pagelanguage",
			"=": "="
		},
		[
			"原始",
			"raw",
			"msg"
		],
		[
			"替代",
			"subst",
			"安全替代",
			"safesubst"
		]
	],
	"doubleUnderscore": [
		[],
		[],
		{
			"forcetoc": "forcetoc",
			"强显目录": "forcetoc",
			"nocc": "nocontentconvert",
			"nocontentconvert": "nocontentconvert",
			"不转换内容": "nocontentconvert",
			"noeditsection": "noeditsection",
			"无段落编辑": "noeditsection",
			"无编辑段落": "noeditsection",
			"nogallery": "nogallery",
			"无图库": "nogallery",
			"notc": "notitleconvert",
			"notitleconvert": "notitleconvert",
			"不转换标题": "notitleconvert",
			"notoc": "notoc",
			"无目录": "notoc",
			"toc": "toc",
			"目录": "toc"
		},
		{
			"EXPECTUNUSEDCATEGORY": "EXPECTUNUSEDCATEGORY",
			"HIDDENCAT": "HIDDENCAT",
			"隐藏分类": "HIDDENCAT",
			"INDEX": "INDEX",
			"索引": "INDEX",
			"NEWSECTIONLINK": "NEWSECTIONLINK",
			"新段落链接": "NEWSECTIONLINK",
			"NOINDEX": "NOINDEX",
			"无索引": "NOINDEX",
			"NONEWSECTIONLINK": "NONEWSECTIONLINK",
			"无新段落链接": "NONEWSECTIONLINK",
			"STATICREDIRECT": "STATICREDIRECT",
			"静态重定向": "STATICREDIRECT"
		}
	],
	"protocol": "bitcoin:|ftp://|ftps://|geo:|git://|gopher://|http://|https://|irc://|ircs://|magnet:|mailto:|matrix:|mms://|news:|nntp://|redis://|sftp://|sip:|sips:|sms:|ssh://|svn://|tel:|telnet://|urn:|worldwind://|xmpp:",
	"interwiki": [],
	"img": {
		"thumbnail": "thumbnail",
		"thumb": "thumbnail",
		"缩略图": "thumbnail",
		"thumbnail=$1": "manualthumb",
		"thumb=$1": "manualthumb",
		"缩略图=$1": "manualthumb",
		"left": "left",
		"左": "left",
		"right": "right",
		"右": "right",
		"none": "none",
		"无": "none",
		"$1px": "width",
		"$1像素": "width",
		"center": "center",
		"centre": "center",
		"居中": "center",
		"framed": "framed",
		"enframed": "framed",
		"frame": "framed",
		"有框": "framed",
		"frameless": "frameless",
		"无框": "frameless",
		"upright": "upright",
		"右上": "upright",
		"upright=$1": "upright",
		"upright $1": "upright",
		"右上=$1": "upright",
		"右上$1": "upright",
		"border": "border",
		"边框": "border",
		"alt=$1": "alt",
		"替代=$1": "alt",
		"替代文本=$1": "alt",
		"class=$1": "class",
		"类=$1": "class",
		"link=$1": "link",
		"链接=$1": "link",
		"baseline": "baseline",
		"基线": "baseline",
		"sub": "sub",
		"子": "sub",
		"super": "super",
		"sup": "super",
		"超": "super",
		"top": "top",
		"顶部": "top",
		"text-top": "text-top",
		"文字顶部": "text-top",
		"middle": "middle",
		"中间": "middle",
		"bottom": "bottom",
		"底部": "bottom",
		"text-bottom": "text-bottom",
		"文字底部": "text-bottom",
		"lang=$1": "lang",
		"语言=$1": "lang",
		"page=$1": "page",
		"page $1": "page",
		"页数=$1": "page",
		"$1页": "page"
	},
	"redirection": [
		"#redirect",
		"#重定向"
	],
	"variants": [
		"zh",
		"zh-hans",
		"zh-hant",
		"zh-cn",
		"zh-tw",
		"zh-hk",
		"zh-sg",
		"zh-my",
		"zh-mo"
	],
	"articlePath": "/zh/$1"
}
